{"sections":{"breadcrumbs":{"type":"breadcrumbs","settings":{}},"main-product":{"type":"main-product","blocks":{"vendor_sku_nA797T":{"type":"vendor_sku","settings":{"show_vendor":true,"show_vendor_link":true,"show_sku":true}},"title":{"type":"title","settings":{"uppercase":false,"show_products_rating":true,"show_products_rating_average":true,"show_products_rating_count":true,"show_installments":true,"show_custom_badges":true}},"description_YwaxkQ":{"type":"description","settings":{"show_below_gallery":false}},"955814cd-267a-4315-b47f-77f3976fbf85":{"type":"siblings","settings":{"siblings_collection":"","sibling_color":"","color_picker_size":"regular","margin_bottom":16}},"variant_picker":{"type":"variant_picker","settings":{"picker_type":"button","color_picker":true,"color_picker_size":"large","color_picker_use_variants":true,"variant_is_disabled":true,"sizing_guide_variant":"","sizing_guide_text":"","sizing_guide_icon":"none","sizing_guide_page":""}},"inventory_level_EjD4Fn":{"type":"inventory_level","settings":{"show_inventory_notice":"always","show_inventory_count":"never","inventory_notice_pulse":true,"inventory_notice_bar":false,"inventory_notice_threshold":10,"inventory_notice_base":200}},"buy_buttons":{"type":"buy_buttons","settings":{"show_quantity_selector":true,"show_dynamic_checkout":true,"show_gift_card_recipient":true}},"95b7e00a-0453-4eb0-9cf0-1dae84d8b822":{"type":"side_panel","disabled":true,"settings":{"show_below_gallery":false,"block_heading":"Still deciding?","side_panel_1_label":"Free shipping on all U.S. orders of $40+","side_panel_1_icon":"leather","side_panel_1_content":"","side_panel_1_page":"","side_panel_2_label":"Easy returns and exchanges","side_panel_2_icon":"box","side_panel_2_content":"","side_panel_2_page":"","side_panel_3_label":"60 night money back guarantee","side_panel_3_icon":"washing","side_panel_3_content":"","side_panel_3_page":""}},"49dfa368-74c4-461a-a1bd-97e29dd699ca":{"type":"complementary","settings":{"show_below_gallery":false,"block_heading":"Pairs well with","product_list_limit":3}},"highlight_features_WnhhqH":{"type":"highlight_features","settings":{"show_below_gallery":true,"columns":"2","highlight_1_heading":"Envío gratuito","highlight_1_text":"A partir de 100 € sin IVA el envío te saldrá gratuito!","highlight_1_icon":"star","highlight_2_heading":"5% Descuento","highlight_2_text":"A partir de 200 € sin IVA te damos un descuento del 5%!","highlight_2_icon":"star","highlight_3_heading":"10% Descuento","highlight_3_text":"A partir de 500 € sin IVA te damos un descuento del 10%!","highlight_3_icon":"star","highlight_4_heading":"15% Descuento","highlight_4_text":"A partir de 1000 € sin IVA te damos un descuento del 10%!","highlight_4_icon":"star","highlight_5_heading":"","highlight_5_text":"","highlight_5_icon":"fire","highlight_6_heading":"","highlight_6_text":"","highlight_6_icon":"ruler"}},"payment_security_wPeMQP":{"type":"payment_security","settings":{"show_below_gallery":false,"has_background":true,"heading":"Pago y seguridad","show_payment_icons":true,"text":"La información de tu pago se procesa de manera segura. No almacenamos los datos de tu tarjeta de crédito ni tenemos acceso a la información de tu tarjeta.","security_image_width":30,"security_heading":"","security_text":"","color_text":"#4f2e83"}},"image_C3QNmF":{"type":"image","settings":{"show_below_gallery":false,"position":"text-left","image_link":""}}},"block_order":["vendor_sku_nA797T","title","description_YwaxkQ","955814cd-267a-4315-b47f-77f3976fbf85","variant_picker","inventory_level_EjD4Fn","buy_buttons","95b7e00a-0453-4eb0-9cf0-1dae84d8b822","49dfa368-74c4-461a-a1bd-97e29dd699ca","highlight_features_WnhhqH","payment_security_wPeMQP","image_C3QNmF"],"settings":{"enable_sticky_add_to_cart":true,"outline_button":true,"show_taxes_included":true,"thumbnail_position":"bottom","product_media_width":"medium","media_aspect_ratio":"adapt","display_captions":true,"hide_variants":true,"lightbox":true,"enable_video_looping":false}},"spacer_6mjDPj":{"type":"spacer","settings":{"spacer_mobile":0,"spacer_desktop":80,"border_separator":true,"border_separator_full":false}},"product_recommendations_NKiVnX":{"type":"product-recommendations","settings":{"heading":"Esto te podría interesar","description":"","product_limit":5,"columns_desktop":5,"disable_top_spacing":true,"disable_bottom_spacing":false}},"17144927127391ffb0":{"type":"apps","settings":{}}},"order":["breadcrumbs","main-product","spacer_6mjDPj","product_recommendations_NKiVnX","17144927127391ffb0"]}